pythonvideoannotator_module_createpaths/__init__.py
pythonvideoannotator_module_createpaths/module.py
pythonvideoannotator_module_createpaths/models/__init__.py
pythonvideoannotator_module_createpaths/models/video/__init__.py
pythonvideoannotator_module_createpaths/models/video/objects/__init__.py
pythonvideoannotator_module_createpaths/models/video/objects/object2d/__init__.py
pythonvideoannotator_module_createpaths/models/video/objects/object2d/datasets/__init__.py
pythonvideoannotator_module_createpaths/models/video/objects/object2d/datasets/contours/__init__.py
pythonvideoannotator_module_createpaths/models/video/objects/object2d/datasets/contours/createpaths_contours.py
Python_video_annotator_module_create_paths-0.5.15.dist-info/METADATA
Python_video_annotator_module_create_paths-0.5.15.dist-info/WHEEL
Python_video_annotator_module_create_paths-0.5.15.dist-info/top_level.txt
Python_video_annotator_module_create_paths-0.5.15.dist-info/RECORD
