Metadata-Version: 2.1
Name: Python-video-annotator-module-create-paths
Version: 0.5.15
Summary: UNKNOWN
Home-page: https://bitbucket.org/fchampalimaud/pythonvideoannotator-module-createpaths
Author: ['Ricardo Ribeiro']
Author-email: ricardojvr@gmail.com
License: UNKNOWN
Platform: UNKNOWN
